example/__init__.py
example/quickStart.py
rapi_api/__init__.py
rapi_api/config.py
rapi_api/configBuilder.py
rapi_api/proc.py
rapi_api/rapi.py
rapi_api-1.0.0.dist-info/LICENSE
rapi_api-1.0.0.dist-info/METADATA
rapi_api-1.0.0.dist-info/WHEEL
rapi_api-1.0.0.dist-info/top_level.txt
rapi_api-1.0.0.dist-info/RECORD
