Metadata-Version: 2.1
Name: rapi_api
Version: 1.0.0
Summary: Rapi API for Python provides user level api using rapi runner.
Home-page: https://github.com/RapiTest/rapi-api
Author: Rapi Team
Author-email: rapitest.service@gmail.com
License: MIT
Platform: UNKNOWN
Classifier: Programming Language :: Python :: 3.7
Classifier: Programming Language :: Python :: 3.8
Classifier: Programming Language :: Python :: 3.9
Classifier: Programming Language :: Python :: 3.10
Classifier: Programming Language :: Python :: 3.11
Requires-Python: >=3.7
License-File: LICENSE
